<?xml version="1.0" encoding="UTF-8"?>
<root t='150' id='1' V150='13' creationTimestamp='0x188482bfd92' V1='4' name='INT_STRUCT_01' incarnation='32'>
  <rootElem t='167' id='6' V167='21' V283='2' occurMinTimes='1' occurMaxTimes='-1' minSize='-1' maxSize='-1' groupType='1' repHandlerStruct='' visible='true' inheritsFrom='' V281='13' V1='4' name='INT_ZXMATM01'>
    <structNode t='150' idref='1'/>
    <child t='167' id='7' V167='21' V283='2' occurMaxTimes='1' minSize='-1' maxSize='-1' dataType='2' repHandlerStruct='' visible='true' inheritsFrom='' V281='13' V1='4' name='MATNR'>
      <structNode t='150' idref='1'/>
    </child>
    <child t='167' id='8' V167='21' V283='2' occurMaxTimes='1' minSize='-1' maxSize='-1' dataType='2' repHandlerStruct='' visible='true' inheritsFrom='' V281='13' V1='4' name='BRGEW'>
      <structNode t='150' idref='1'/>
    </child>
    <child t='167' id='9' V167='21' V283='2' occurMaxTimes='1' minSize='-1' maxSize='-1' dataType='2' repHandlerStruct='' visible='true' inheritsFrom='' V281='13' V1='4' name='GEWEI'>
      <structNode t='150' idref='1'/>
    </child>
    <child t='167' id='10' V167='21' V283='2' occurMaxTimes='1' minSize='-1' maxSize='-1' dataType='2' repHandlerStruct='' visible='true' inheritsFrom='' V281='13' V1='4' name='VOLUM'>
      <structNode t='150' idref='1'/>
    </child>
    <child t='167' id='11' V167='21' V283='2' occurMaxTimes='1' minSize='-1' maxSize='-1' dataType='2' repHandlerStruct='' visible='true' inheritsFrom='' V281='13' V1='4' name='LAENG'>
      <structNode t='150' idref='1'/>
    </child>
    <child t='167' id='12' V167='21' V283='2' occurMaxTimes='1' minSize='-1' maxSize='-1' dataType='2' repHandlerStruct='' visible='true' inheritsFrom='' V281='13' V1='4' name='BREIT'>
      <structNode t='150' idref='1'/>
    </child>
    <child t='167' id='13' V167='21' V283='2' occurMaxTimes='1' minSize='-1' maxSize='-1' dataType='2' repHandlerStruct='' visible='true' inheritsFrom='' V281='13' V1='4' name='HOEHE'>
      <structNode t='150' idref='1'/>
    </child>
    <child t='167' id='14' V167='21' V283='2' occurMaxTimes='1' minSize='-1' maxSize='-1' dataType='2' repHandlerStruct='' visible='true' inheritsFrom='' V281='13' V1='4' name='CHARACTERISTIC'>
      <structNode t='150' idref='1'/>
    </child>
    <child t='167' id='15' V167='21' V283='2' occurMaxTimes='1' minSize='-1' maxSize='-1' dataType='2' repHandlerStruct='' visible='true' inheritsFrom='' V281='13' V1='4' name='CHARCDATATYPE'>
      <structNode t='150' idref='1'/>
    </child>
    <child t='167' id='16' V167='21' V283='2' occurMaxTimes='1' minSize='-1' maxSize='-1' dataType='2' repHandlerStruct='' visible='true' inheritsFrom='' V281='13' V1='4' name='CHARCVALUEINTERVALTYPE'>
      <structNode t='150' idref='1'/>
    </child>
    <child t='167' id='17' V167='21' V283='2' occurMaxTimes='1' minSize='-1' maxSize='-1' dataType='2' repHandlerStruct='' visible='true' inheritsFrom='' V281='13' V1='4' name='CHARCFROMNUMERICVALUE'>
      <structNode t='150' idref='1'/>
    </child>
    <child t='167' id='18' V167='21' V283='2' occurMaxTimes='1' minSize='-1' maxSize='-1' dataType='2' repHandlerStruct='' visible='true' inheritsFrom='' V281='13' V1='4' name='CHARCTONUMERICVALUE'>
      <structNode t='150' idref='1'/>
    </child>
    <child t='167' id='19' V167='21' V283='2' occurMaxTimes='1' minSize='-1' maxSize='-1' dataType='2' repHandlerStruct='' visible='true' inheritsFrom='' V281='13' V1='4' name='CHARCFROMDECIMALVALUE'>
      <structNode t='150' idref='1'/>
    </child>
    <child t='167' id='20' V167='21' V283='2' occurMaxTimes='1' minSize='-1' maxSize='-1' dataType='2' repHandlerStruct='' visible='true' inheritsFrom='' V281='13' V1='4' name='CHARCTODECIMALVALUE'>
      <structNode t='150' idref='1'/>
    </child>
    <child t='167' id='21' V167='21' V283='2' occurMaxTimes='1' minSize='-1' maxSize='-1' dataType='2' repHandlerStruct='' visible='true' inheritsFrom='' V281='13' V1='4' name='CHARCFROMAMOUNT'>
      <structNode t='150' idref='1'/>
    </child>
    <child t='167' id='22' V167='21' V283='2' occurMaxTimes='1' minSize='-1' maxSize='-1' dataType='2' repHandlerStruct='' visible='true' inheritsFrom='' V281='13' V1='4' name='CHARCTOAMOUNT'>
      <structNode t='150' idref='1'/>
    </child>
    <child t='167' id='23' V167='21' V283='2' occurMaxTimes='1' minSize='-1' maxSize='-1' dataType='2' repHandlerStruct='' visible='true' inheritsFrom='' V281='13' V1='4' name='CHARCFROMDATE'>
      <structNode t='150' idref='1'/>
    </child>
    <child t='167' id='24' V167='21' V283='2' occurMaxTimes='1' minSize='-1' maxSize='-1' dataType='2' repHandlerStruct='' visible='true' inheritsFrom='' V281='13' V1='4' name='CHARCTODATE'>
      <structNode t='150' idref='1'/>
    </child>
    <child t='167' id='25' V167='21' V283='2' occurMaxTimes='1' minSize='-1' maxSize='-1' dataType='2' repHandlerStruct='' visible='true' inheritsFrom='' V281='13' V1='4' name='CHARCFROMTIME'>
      <structNode t='150' idref='1'/>
    </child>
    <child t='167' id='26' V167='21' V283='2' occurMaxTimes='1' minSize='-1' maxSize='-1' dataType='2' repHandlerStruct='' visible='true' inheritsFrom='' V281='13' V1='4' name='CHARCTOTIME'>
      <structNode t='150' idref='1'/>
    </child>
  </rootElem>
  <defaultRep t='183' id='2' V183='1' V170='10' V706='1' defaultHeader='Col' delimiter=',' quoteCharacter='"' quoteMode='4' newLine='&#xD;&#xA;' V690='1' encoding='UTF-8' ignoreExcluded='true' fixInvalidCharacters='true' V1='4' name='CSV'>
  </defaultRep>
  <child t='162' id='3' V1='4' name='Representations'>
    <child t='183' idref='2'/>
    <child t='172' id='4' V172='6' autoFixNamespaceMismatch='true' V170='10' V692='1' V690='1' ignoreExcluded='true' fixInvalidCharacters='true' V1='4' name='XML'>
    </child>
  </child>
  <child t='165' id='5' V1='4' name='Document Bindings'>
    <child t='166' id='27' V166='5' docType='1' V1='4'>
      <structNode t='150' idref='1'/>
    </child>
  </child>
</root>
