<?xml version="1.0" encoding="UTF-8"?>
<root t='150' id='1' V150='13' creationTimestamp='0x18967ef6eeb' V1='4' name='LOGIMATSDACK00004' incarnation='13'>
  <rootElem t='167' id='2' V167='21' V283='2' occurMaxTimes='1' minSize='-1' maxSize='-1' groupType='1' repHandlerStruct='' visible='true' inheritsFrom='' V281='13' V1='4' name='root'>
    <structNode t='150' idref='1'/>
    <child t='167' id='3' V167='21' V283='2' occurMinTimes='1' occurMaxTimes='9999' minSize='-1' maxSize='-1' groupType='1' repHandlerStruct='' visible='true' nullable='true' inheritsFrom='' V281='13' V1='4' name='StorageDemandeResponse'>
      <structNode t='150' idref='1'/>
      <child t='167' id='4' V167='21' V283='2' occurMaxTimes='1' minSize='-1' maxSize='-1' dataType='2' repHandlerStruct='' visible='true' nullable='true' inheritsFrom='' V281='13' V1='4' name='LogimatStorageDemand_demandNo'>
        <structNode t='150' idref='1'/>
      </child>
      <child t='167' id='5' V167='21' V283='2' occurMaxTimes='1' minSize='-1' maxSize='-1' dataType='2' decimalPositions='1' repHandlerStruct='' visible='true' nullable='true' inheritsFrom='' V281='13' V1='4' name='LogimatStorageDemandLine_ToStoredAmount'>
        <structNode t='150' idref='1'/>
      </child>
      <child t='167' id='6' V167='21' V283='2' occurMaxTimes='1' minSize='-1' maxSize='-1' dataType='2' decimalPositions='1' repHandlerStruct='' visible='true' nullable='true' inheritsFrom='' V281='13' V1='4' name='LogimatStorageActivity_storedAmount'>
        <structNode t='150' idref='1'/>
      </child>
      <child t='167' id='7' V167='21' V283='2' occurMaxTimes='1' minSize='-1' maxSize='-1' dataType='2' repHandlerStruct='' visible='true' nullable='true' inheritsFrom='' V281='13' V1='4' name='WHO'>
        <structNode t='150' idref='1'/>
      </child>
      <child t='167' id='8' V167='21' V283='2' occurMaxTimes='1' minSize='-1' maxSize='-1' dataType='2' repHandlerStruct='' visible='true' nullable='true' inheritsFrom='' V281='13' V1='4' name='TANUM'>
        <structNode t='150' idref='1'/>
      </child>
    </child>
  </rootElem>
  <defaultRep t='172' id='9' V172='6' autoFixNamespaceMismatch='true' V170='10' V692='1' unnamedElemsNamespace='1' V690='1' encoding='UTF-8' importDate='Tue Jul 18 09:38:12 CEST 2023' importFile='file:/C:/Work/WAMAS/wamas--sap/LOGIMATSDACK00004/in/LOGIMATSDACK00004_intermedia.xml' ignoreExcluded='true' fixInvalidCharacters='true' V1='4' name='XML'>
    <namespaceContainers t='220' ref='Namespace Containers/WAMAS_LOGIMATSDACK00004.xml'/>
  </defaultRep>
  <child t='162' id='10' V1='4' name='Representations'>
    <child t='172' idref='9'/>
  </child>
  <child t='165' id='11' V1='4' name='Document Bindings'>
    <child t='166' id='12' V166='5' docType='1' docReposPath='/WOHO_WORKSPACE/Sample Data/WAMAS/LOGIMATSDACK00004/LOGIMATSDACK00004/LOGIMATSDACK00004_intermedia' V1='4' name='/root'>
      <elemNode t='167' idref='2'/>
    </child>
  </child>
</root>
